deploybot/__init__.py
deploybot/cli.py
deploybot/commands/__init__.py
deploybot/commands/configure.py
deploybot/commands/ecs.py
deploybot/commands/lambda_.py
deploybot/commands/migrate.py
deploybot/commands/shared.py
deploybot/pyproject.toml
deploybot/utils/__init__.py
deploybot/utils/aws.py
deploybot/utils/config.py
deploybot/utils/parser.py
deploybot/utils/version.py
deploybot-0.4.3.dist-info/METADATA
deploybot-0.4.3.dist-info/WHEEL
deploybot-0.4.3.dist-info/entry_points.txt
deploybot-0.4.3.dist-info/RECORD
