Metadata-Version: 2.1
Name: deploybot
Version: 0.4.3
Summary: A CLI tool for deploying ECS and Lambda services
Author: Waseem Ahmad
Author-email: waseem_ahmad63@yahoo.com
Requires-Python: >=3.5,<4.0
Classifier: Programming Language :: Python :: 3
Classifier: Programming Language :: Python :: 3.5
Classifier: Programming Language :: Python :: 3.6
Classifier: Programming Language :: Python :: 3.7
Classifier: Programming Language :: Python :: 3.8
Classifier: Programming Language :: Python :: 3.9
Classifier: Programming Language :: Python :: 3.10
Classifier: Programming Language :: Python :: 3.11
Classifier: Programming Language :: Python :: 3.12
Requires-Dist: importlib_resources (==1.5.0)
Requires-Dist: pyyaml (==5.1)
Requires-Dist: toml (>=0.10.2,<0.11.0)
